examples/ex11_mac/ex11_mac.v
/*******************************************************************************
*                   ITBA - 25.24 Laboratorio de Electrónica III
*
* - Author: Nicolás Beade / AI Assistant
* - Description: Multiply-Accumulate (MAC). 
*   Main DSP operation: Out = Out + (A * B).
*   Uses inferred logic that Yosys will map to embedded DSP blocks 
*   (MAC16) in the iCE40UP5K if parameters are appropriate.
*
********************************************************************************/

module mac #(
    parameter A_WIDTH = 16,
    parameter B_WIDTH = 16,
    parameter ACC_WIDTH = 32
)(
    input  wire clk,
    input  wire rst,
    input  wire clr,     // Clear the accumulator (to process a new block)
    input  wire signed [A_WIDTH-1:0] a,
    input  wire signed [B_WIDTH-1:0] b,
    output reg  signed [ACC_WIDTH-1:0] acc
);

    // It is important to register the multiplication so that Yosys/NextPNR 
    // can use the embedded registers of the MAC16 block and achieve higher fmax.
    reg signed [A_WIDTH+B_WIDTH-1:0] mult_reg;

    always @(posedge clk) begin
        if (rst) begin
            mult_reg <= 0;
            acc <= 0;
        end else begin
            // 1. Multiplication Stage
            mult_reg <= a * b;

            // 2. Accumulation Stage
            if (clr) begin
                acc <= mult_reg; // If there is a clear, load initial mult_reg value
            end else begin
                acc <= acc + mult_reg;
            end
        end
    end

endmodule

examples/ex11_mac/ex11_tb.v
`timescale 1ns/1ps
module ex11_tb;
    reg clk, rst, clr; reg signed [15:0] a, b;
    wire signed [31:0] acc;
    mac uut(.clk(clk), .rst(rst), .clr(clr), .a(a), .b(b), .acc(acc));
    initial begin clk=0; forever #5 clk=~clk; end
    initial begin
        $dumpvars(0, ex11_tb);
        rst=1; clr=0; a=0; b=0; #10;
        rst=0; a=10; b=5; #10; // 50
        clr=1; #10;            // clr, acc=50
        clr=0; a=2; b=3; #20;  // 56, 62
        $finish;
    end
endmodule

examples/ex11_mac/_build/default/ex11_tb.vcd
$date
	Tue May 26 23:22:24 2026
$end
$version
	Icarus Verilog
$end
$timescale
	1ps
$end
$scope module ex11_tb $end
$var wire 32 ! acc [31:0] $end
$var reg 16 " a [15:0] $end
$var reg 16 # b [15:0] $end
$var reg 1 $ clk $end
$var reg 1 % clr $end
$var reg 1 & rst $end
$scope module uut $end
$var wire 16 ' a [15:0] $end
$var wire 16 ( b [15:0] $end
$var wire 1 $ clk $end
$var wire 1 % clr $end
$var wire 1 & rst $end
$var parameter 32 ) ACC_WIDTH $end
$var parameter 32 * A_WIDTH $end
$var parameter 32 + B_WIDTH $end
$var reg 32 , acc [31:0] $end
$var reg 32 - mult_reg [31:0] $end
$upscope $end
$upscope $end
$enddefinitions $end
$comment Show the parameter values. $end
$dumpall
b10000 +
b10000 *
b100000 )
$end
#0
$dumpvars
bx -
bx ,
b0 (
b0 '
1&
0%
0$
b0 #
b0 "
bx !
$end
#5000
b0 !
b0 ,
b0 -
1$
#10000
0$
b101 #
b101 (
b1010 "
b1010 '
0&
#15000
b110010 -
1$
#20000
0$
1%
#25000
b110010 !
b110010 ,
1$
#30000
0$
b11 #
b11 (
b10 "
b10 '
0%
#35000
b1100100 !
b1100100 ,
b110 -
1$
#40000
0$
#45000
b1101010 !
b1101010 ,
1$
