examples/ex10_fir_filter/ex9_regressor.v
/*******************************************************************************
*                   ITBA - 25.24 Laboratorio de Electrónica III
*
* - Author: Nicolás Beade / AI Assistant
* - Description: Delay Line (Regressor or Tapped Delay Line).
*   On each clock cycle, it shifts the data, keeping a history of the 
*   previous samples. It is the fundamental memory block for FIR digital filters.
*
********************************************************************************/

module regressor #(
    parameter DATA_WIDTH = 8,
    parameter TAPS = 4 // Number of samples kept in history
)(
    input  wire clk,
    input  wire rst,
    input  wire signed [DATA_WIDTH-1:0] data_in,
    // Flat output to facilitate portability.
    // It will have a width of DATA_WIDTH * TAPS
    output wire [(DATA_WIDTH * TAPS) - 1 : 0] flat_taps
);

    // Memory for the delays
    reg signed [DATA_WIDTH-1:0] delay_line [0:TAPS-1];

    integer i;

    always @(posedge clk) begin
        if (rst) begin
            for (i = 0; i < TAPS; i = i + 1) begin
                delay_line[i] <= 0;
            end
        end else begin
            // Shift samples: The highest index (oldest) receives the previous one
            for (i = TAPS-1; i > 0; i = i - 1) begin
                delay_line[i] <= delay_line[i-1];
            end
            // Position 0 (newest) receives the input data
            delay_line[0] <= data_in;
        end
    end

    // Pack the memory positions into the flat output
    genvar j;
    generate
        for (j = 0; j < TAPS; j = j + 1) begin : pack
            assign flat_taps[(j+1)*DATA_WIDTH - 1 : j*DATA_WIDTH] = delay_line[j];
        end
    endgenerate

endmodule

examples/ex10_fir_filter/ex10_fir_filter.v
/*******************************************************************************
*                   ITBA - 25.24 Laboratorio de Electrónica III
*
* - Author: Nicolás Beade / AI Assistant
* - Description: Complete FIR Filter instantiating the Regressor (ex9).
*   Each TAP (delayed sample) is multiplied by a constant coefficient
*   and then all products are summed using an Adder Tree (ex8).
*
********************************************************************************/

module fir_filter #(
    parameter IN_WIDTH = 8,
    parameter COEF_WIDTH = 8
)(
    input  wire clk,
    input  wire rst,
    input  wire signed [IN_WIDTH-1:0] din,
    // The multiplier width is IN_WIDTH + COEF_WIDTH.
    // The sum of 4 multiplications requires 2 extra bits (log2(4)).
    output reg  signed [IN_WIDTH + COEF_WIDTH + 1 : 0] dout
);

    localparam TAPS = 4;
    localparam MULT_WIDTH = IN_WIDTH + COEF_WIDTH;

    // Fixed filter coefficients (Could be calculated in MATLAB/Python)
    wire signed [COEF_WIDTH-1:0] h [0:3];
    assign h[0] = 8'd10;
    assign h[1] = 8'd20;
    assign h[2] = 8'd20;
    assign h[3] = 8'd10;

    // --- 1. Instantiate the Regressor (Filter Memory) ---
    wire [(IN_WIDTH * TAPS) - 1 : 0] flat_taps;
    regressor #(
        .DATA_WIDTH(IN_WIDTH),
        .TAPS(TAPS)
    ) delay_line_inst (
        .clk(clk),
        .rst(rst),
        .data_in(din),
        .flat_taps(flat_taps)
    );

    // --- 2. Combinational Multiplication ---
    // Extract the delays from the regressor
    wire signed [IN_WIDTH-1:0] tap0 = flat_taps[  IN_WIDTH-1 : 0];
    wire signed [IN_WIDTH-1:0] tap1 = flat_taps[2*IN_WIDTH-1 :   IN_WIDTH];
    wire signed [IN_WIDTH-1:0] tap2 = flat_taps[3*IN_WIDTH-1 : 2*IN_WIDTH];
    wire signed [IN_WIDTH-1:0] tap3 = flat_taps[4*IN_WIDTH-1 : 3*IN_WIDTH];

    /*
    wire signed [MULT_WIDTH-1:0] prod0 = tap0 * h[0];
    wire signed [MULT_WIDTH-1:0] prod1 = tap1 * h[1];
    wire signed [MULT_WIDTH-1:0] prod2 = tap2 * h[2];
    wire signed [MULT_WIDTH-1:0] prod3 = tap3 * h[3];

    
    // Pack products to send them to the adder_tree
    wire [(MULT_WIDTH * TAPS) - 1 : 0] flat_prods;
    assign flat_prods = {prod3, prod2, prod1, prod0};

    // --- 3. Adder Tree ---
    wire [MULT_WIDTH + 1 : 0] sum_wire;
    adder_tree #(
        .IN_WIDTH(MULT_WIDTH),
        .NUM_INPUTS(TAPS)
    ) sum_tree_inst (
        .flat_inputs(flat_prods),
        .sum_out(sum_wire)
    );
    */

    // Podemos aprovechar la simetria de los coeficientes para reducir el numero de multiplicaciones
    wire signed [MULT_WIDTH-1:0] prod01 = (tap0 + tap3) * h[0]; // h[0] = h[3]

    wire signed [MULT_WIDTH-1:0] prod12 = (tap1 + tap2) * h[1]; // h[1] = h[2]

    //Hacemos la suma agregando 1 bit para evitar overflow
    wire signed [MULT_WIDTH + 1 : 0] sum_wire = prod01 + prod12; 

    // --- 4. Register Output ---
    always @(posedge clk) begin
        if (rst) begin
            dout <= 0;
        end else begin
            dout <= sum_wire; // Output pipelining
        end
    end

endmodule

examples/ex10_fir_filter/ex10_tb.v
`timescale 1ns/1ps
module ex10_tb;
    reg clk, rst; reg signed [7:0] din;
    wire signed [17:0] dout;
    fir_filter uut(.clk(clk), .rst(rst), .din(din), .dout(dout));
    initial begin clk=0; forever #5 clk=~clk; end
    initial begin
        $dumpvars(0, ex10_tb);
        rst=1; din=0; #10;
        rst=0; din=100; #10;
        din=0; #50;
        $finish;
    end
endmodule

examples/ex10_fir_filter/_build/default/ex10_tb.vcd
$date
	Wed May 27 21:31:45 2026
$end
$version
	Icarus Verilog
$end
$timescale
	1ps
$end
$scope module ex10_tb $end
$var wire 18 ! dout [17:0] $end
$var reg 1 " clk $end
$var reg 8 # din [7:0] $end
$var reg 1 $ rst $end
$scope module uut $end
$var wire 1 " clk $end
$var wire 8 % din [7:0] $end
$var wire 1 $ rst $end
$var wire 8 & tap3 [7:0] $end
$var wire 8 ' tap2 [7:0] $end
$var wire 8 ( tap1 [7:0] $end
$var wire 8 ) tap0 [7:0] $end
$var wire 18 * sum_wire [17:0] $end
$var wire 16 + prod12 [15:0] $end
$var wire 16 , prod01 [15:0] $end
$var wire 32 - flat_taps [31:0] $end
$var parameter 32 . COEF_WIDTH $end
$var parameter 32 / IN_WIDTH $end
$var parameter 33 0 MULT_WIDTH $end
$var parameter 32 1 TAPS $end
$var reg 18 2 dout [17:0] $end
$scope module delay_line_inst $end
$var wire 1 " clk $end
$var wire 8 3 data_in [7:0] $end
$var wire 1 $ rst $end
$var wire 32 4 flat_taps [31:0] $end
$var parameter 32 5 DATA_WIDTH $end
$var parameter 32 6 TAPS $end
$var integer 32 7 i [31:0] $end
$scope begin pack[0] $end
$var parameter 2 8 j $end
$upscope $end
$scope begin pack[1] $end
$var parameter 2 9 j $end
$upscope $end
$scope begin pack[2] $end
$var parameter 3 : j $end
$upscope $end
$scope begin pack[3] $end
$var parameter 3 ; j $end
$upscope $end
$upscope $end
$upscope $end
$upscope $end
$enddefinitions $end
$comment Show the parameter values. $end
$dumpall
b11 ;
b10 :
b1 9
b0 8
b100 6
b1000 5
b100 1
b10000 0
b1000 /
b1000 .
$end
#0
$dumpvars
bx 7
bx 4
b0 3
bx 2
bx -
bx ,
bx +
bx *
bx )
bx (
bx '
bx &
b0 %
1$
b0 #
0"
bx !
$end
#5000
b0 *
b0 ,
b0 &
b0 +
b0 '
b0 (
b0 )
b0 -
b0 4
b0 !
b0 2
b100 7
1"
#10000
0"
b1100100 #
b1100100 %
b1100100 3
0$
#15000
b1111101000 *
b1111101000 ,
b1100100 )
b1100100 -
b1100100 4
b0 7
1"
#20000
0"
b0 #
b0 %
b0 3
#25000
b11111010000 +
b1100100 (
b11111010000 *
b0 ,
b0 )
b110010000000000 -
b110010000000000 4
b1111101000 !
b1111101000 2
b0 7
1"
#30000
0"
#35000
b1100100 '
b11111010000 *
b11111010000 +
b0 (
b11001000000000000000000 -
b11001000000000000000000 4
b11111010000 !
b11111010000 2
b0 7
1"
#40000
0"
#45000
b1111101000 ,
b1100100 &
b1111101000 *
b0 +
b0 '
b1100100000000000000000000000000 -
b1100100000000000000000000000000 4
b0 7
1"
#50000
0"
#55000
b0 *
b0 ,
b0 &
b0 -
b0 4
b1111101000 !
b1111101000 2
b0 7
1"
#60000
0"
#65000
b0 !
b0 2
b0 7
1"
