examples/ex10_fir_filter/ex9_regressor.v
/*******************************************************************************
*                   ITBA - 25.24 Laboratorio de Electrónica III
*
* - Author: Nicolás Beade / AI Assistant
* - Description: Delay Line (Regressor or Tapped Delay Line).
*   On each clock cycle, it shifts the data, keeping a history of the 
*   previous samples. It is the fundamental memory block for FIR digital filters.
*
********************************************************************************/

module regressor #(
    parameter DATA_WIDTH = 8,
    parameter TAPS = 4 // Number of samples kept in history
)(
    input  wire clk,
    input  wire rst,
    input  wire signed [DATA_WIDTH-1:0] data_in,
    // Flat output to facilitate portability.
    // It will have a width of DATA_WIDTH * TAPS
    output wire [(DATA_WIDTH * TAPS) - 1 : 0] flat_taps
);

    // Memory for the delays
    reg signed [DATA_WIDTH-1:0] delay_line [0:TAPS-1];

    integer i;

    always @(posedge clk) begin
        if (rst) begin
            for (i = 0; i < TAPS; i = i + 1) begin
                delay_line[i] <= 0;
            end
        end else begin
            // Shift samples: The highest index (oldest) receives the previous one
            for (i = TAPS-1; i > 0; i = i - 1) begin
                delay_line[i] <= delay_line[i-1];
            end
            // Position 0 (newest) receives the input data
            delay_line[0] <= data_in;
        end
    end

    // Pack the memory positions into the flat output
    genvar j;
    generate
        for (j = 0; j < TAPS; j = j + 1) begin : pack
            assign flat_taps[(j+1)*DATA_WIDTH - 1 : j*DATA_WIDTH] = delay_line[j];
        end
    endgenerate

endmodule

examples/ex9_regressor/ex9_tb.v
`timescale 1ns/1ps
module ex9_tb;
    reg clk, rst; reg signed [7:0] din;
    wire [31:0] taps;
    regressor uut(.clk(clk), .rst(rst), .data_in(din), .flat_taps(taps));
    initial begin clk=0; forever #5 clk=~clk; end
    initial begin
        $dumpvars(0, ex9_tb);
        rst=1; din=0; #10;
        rst=0; din=10; #10;
        din=20; #10; din=30; #20;
        $finish;
    end
endmodule

examples/ex9_regressor/_build/default/ex9_tb.vcd
$date
	Tue May 26 23:18:36 2026
$end
$version
	Icarus Verilog
$end
$timescale
	1ps
$end
$scope module ex9_tb $end
$var wire 32 ! taps [31:0] $end
$var reg 1 " clk $end
$var reg 8 # din [7:0] $end
$var reg 1 $ rst $end
$scope module uut $end
$var wire 1 " clk $end
$var wire 8 % data_in [7:0] $end
$var wire 1 $ rst $end
$var wire 32 & flat_taps [31:0] $end
$var parameter 32 ' DATA_WIDTH $end
$var parameter 32 ( TAPS $end
$var integer 32 ) i [31:0] $end
$scope begin pack[0] $end
$var parameter 2 * j $end
$upscope $end
$scope begin pack[1] $end
$var parameter 2 + j $end
$upscope $end
$scope begin pack[2] $end
$var parameter 3 , j $end
$upscope $end
$scope begin pack[3] $end
$var parameter 3 - j $end
$upscope $end
$upscope $end
$upscope $end
$enddefinitions $end
$comment Show the parameter values. $end
$dumpall
b11 -
b10 ,
b1 +
b0 *
b100 (
b1000 '
$end
#0
$dumpvars
bx )
bx &
b0 %
1$
b0 #
0"
bx !
$end
#5000
b0 !
b0 &
b100 )
1"
#10000
0"
b1010 #
b1010 %
0$
#15000
b1010 !
b1010 &
b0 )
1"
#20000
0"
b10100 #
b10100 %
#25000
b101000010100 !
b101000010100 &
b0 )
1"
#30000
0"
b11110 #
b11110 %
#35000
b10100001010000011110 !
b10100001010000011110 &
b0 )
1"
#40000
0"
#45000
b1010000101000001111000011110 !
b1010000101000001111000011110 &
b0 )
1"
