examples/ex12_sine_lut/ex12_sine_lut.v
/*******************************************************************************
*                   ITBA - 25.24 Laboratorio de Electrónica III
*
* - Author: Nicolás Beade / AI Assistant
* - Description: Sine Look-Up Table (LUT) or Direct Digital Synthesis (DDS).
*   Generates a pre-calculated sine wave. The phase acts as an 
*   accumulator that addresses the ROM table.
*
*   ROM values should be generated from Python/MATLAB and loaded into Verilog.
*   Here we assume a ROM synthesized via combinational always blocks 
*   or $readmemh initializing an internal memory.
*
********************************************************************************/

module sine_lut #(
    parameter PHASE_WIDTH = 8, // 256 samples for a full cycle
    parameter DATA_WIDTH  = 8
)(
    input  wire clk,
    input  wire rst,
    input  wire [PHASE_WIDTH-1:0] phase_inc, // Frequency (phase increment)
    output reg signed [DATA_WIDTH-1:0] sine_out
);

    // Phase accumulator
    reg [PHASE_WIDTH-1:0] phase_acc;

    always @(posedge clk) begin
        if (rst) begin
            phase_acc <= 0;
        end else begin
            phase_acc <= phase_acc + phase_inc;
        end
    end

    // LUT: We assume a 16-position wave for simplicity of the example.
    // In a real case, this would be a RAM initialized with $readmemh.
    always @(posedge clk) begin
        // Using the 4 most significant bits of the accumulator to address 16 positions.
        case (phase_acc[PHASE_WIDTH-1 : PHASE_WIDTH-4])
            4'd0:  sine_out <=  8'd0;
            4'd1:  sine_out <=  8'd49;
            4'd2:  sine_out <=  8'd90;
            4'd3:  sine_out <=  8'd117;
            4'd4:  sine_out <=  8'd127;
            4'd5:  sine_out <=  8'd117;
            4'd6:  sine_out <=  8'd90;
            4'd7:  sine_out <=  8'd49;
            4'd8:  sine_out <=  8'd0;
            4'd9:  sine_out <= -8'd49;
            4'd10: sine_out <= -8'd90;
            4'd11: sine_out <= -8'd117;
            4'd12: sine_out <= -8'd127;
            4'd13: sine_out <= -8'd117;
            4'd14: sine_out <= -8'd90;
            4'd15: sine_out <= -8'd49;
            default: sine_out <= 8'd0;
        endcase
    end

endmodule

examples/ex12_sine_lut/ex12_tb.v
`timescale 1ns/1ps
module ex12_tb;
    reg clk, rst; reg [7:0] inc;
    wire signed [7:0] sine;
    sine_lut uut(.clk(clk), .rst(rst), .phase_inc(inc), .sine_out(sine));
    initial begin clk=0; forever #5 clk=~clk; end
    initial begin
        $dumpvars(0, ex12_tb);
        rst=1; inc=8'd16; #10;
        rst=0; #200;
        $finish;
    end
endmodule

examples/ex12_sine_lut/_build/default/ex12_tb.vcd
$date
	Tue May 26 23:29:05 2026
$end
$version
	Icarus Verilog
$end
$timescale
	1ps
$end
$scope module ex12_tb $end
$var wire 8 ! sine [7:0] $end
$var reg 1 " clk $end
$var reg 8 # inc [7:0] $end
$var reg 1 $ rst $end
$scope module uut $end
$var wire 1 " clk $end
$var wire 8 % phase_inc [7:0] $end
$var wire 1 $ rst $end
$var parameter 32 & DATA_WIDTH $end
$var parameter 32 ' PHASE_WIDTH $end
$var reg 8 ( phase_acc [7:0] $end
$var reg 8 ) sine_out [7:0] $end
$upscope $end
$upscope $end
$enddefinitions $end
$comment Show the parameter values. $end
$dumpall
b1000 '
b1000 &
$end
#0
$dumpvars
bx )
bx (
b10000 %
1$
b10000 #
0"
bx !
$end
#5000
b0 (
b0 !
b0 )
1"
#10000
0"
0$
#15000
b10000 (
1"
#20000
0"
#25000
b100000 (
b110001 !
b110001 )
1"
#30000
0"
#35000
b1011010 !
b1011010 )
b110000 (
1"
#40000
0"
#45000
b1000000 (
b1110101 !
b1110101 )
1"
#50000
0"
#55000
b1111111 !
b1111111 )
b1010000 (
1"
#60000
0"
#65000
b1100000 (
b1110101 !
b1110101 )
1"
#70000
0"
#75000
b1011010 !
b1011010 )
b1110000 (
1"
#80000
0"
#85000
b10000000 (
b110001 !
b110001 )
1"
#90000
0"
#95000
b0 !
b0 )
b10010000 (
1"
#100000
0"
#105000
b10100000 (
b11001111 !
b11001111 )
1"
#110000
0"
#115000
b10100110 !
b10100110 )
b10110000 (
1"
#120000
0"
#125000
b11000000 (
b10001011 !
b10001011 )
1"
#130000
0"
#135000
b10000001 !
b10000001 )
b11010000 (
1"
#140000
0"
#145000
b11100000 (
b10001011 !
b10001011 )
1"
#150000
0"
#155000
b10100110 !
b10100110 )
b11110000 (
1"
#160000
0"
#165000
b0 (
b11001111 !
b11001111 )
1"
#170000
0"
#175000
b0 !
b0 )
b10000 (
1"
#180000
0"
#185000
b100000 (
b110001 !
b110001 )
1"
#190000
0"
#195000
b1011010 !
b1011010 )
b110000 (
1"
#200000
0"
#205000
b1000000 (
b1110101 !
b1110101 )
1"
